vending_machine.v
//=========================================================
// Vending Machine FSM
// Products:
// Product A = Rs.15
// Product B = Rs.20
//
// Coins Accepted:
// Rs.5 and Rs.10
//
// Features:
// - Handles exact payment
// - Handles extra payment with change return
// - Separate product selection
// - FSM based sequential design
//=========================================================

module vending_machine(
    input clk,
    input reset,

    input coin5,
    input coin10,

    input selectA,     // Product A = 15
    input selectB,     // Product B = 20

    output reg dispenseA,
    output reg dispenseB,
    output reg [4:0] change,
    output reg [5:0] balance
);

    //=====================================================
    // STATE ENCODING
    //=====================================================

    parameter S0  = 0;
    parameter S5  = 1;
    parameter S10 = 2;
    parameter S15 = 3;
    parameter S20 = 4;
    parameter S25 = 5;

    reg [2:0] state, next_state;

    //=====================================================
    // STATE MEMORY
    //=====================================================

    always @(posedge clk or posedge reset)
    begin
        if(reset)
            state <= S0;
        else
            state <= next_state;
    end

    //=====================================================
    // NEXT STATE LOGIC
    //=====================================================

    always @(*)
    begin
        next_state = state;

        case(state)

            //---------------------------------------------
            // Rs.0
            //---------------------------------------------
            S0:
            begin
                if(coin5)
                    next_state = S5;

                else if(coin10)
                    next_state = S10;
            end

            //---------------------------------------------
            // Rs.5
            //---------------------------------------------
            S5:
            begin
                if(coin5)
                    next_state = S10;

                else if(coin10)
                    next_state = S15;
            end

            //---------------------------------------------
            // Rs.10
            //---------------------------------------------
            S10:
            begin
                if(coin5)
                    next_state = S15;

                else if(coin10)
                    next_state = S20;
            end

            //---------------------------------------------
            // Rs.15
            //---------------------------------------------
            S15:
            begin
                if(coin5)
                    next_state = S20;

                else if(coin10)
                    next_state = S25;
            end

            //---------------------------------------------
            // Rs.20
            //---------------------------------------------
            S20:
            begin
                if(coin5)
                    next_state = S25;
            end

            //---------------------------------------------
            // Rs.25
            //---------------------------------------------
            S25:
            begin
                next_state = S25;
            end

            default:
                next_state = S0;

        endcase
    end

    //=====================================================
    // OUTPUT LOGIC
    //=====================================================

    always @(*)
    begin

        dispenseA = 0;
        dispenseB = 0;
        change = 0;

        case(state)

            //-------------------------------------------------
            // PRODUCT A (Rs.15)
            //-------------------------------------------------

            S15:
            begin
                if(selectA)
                begin
                    dispenseA = 1;
                    change = 0;
                end
            end

            S20:
            begin
                if(selectA)
                begin
                    dispenseA = 1;
                    change = 5;
                end

                else if(selectB)
                begin
                    dispenseB = 1;
                    change = 0;
                end
            end

            S25:
            begin
                if(selectA)
                begin
                    dispenseA = 1;
                    change = 10;
                end

                else if(selectB)
                begin
                    dispenseB = 1;
                    change = 5;
                end
            end

        endcase
    end

    //=====================================================
    // BALANCE DISPLAY
    //=====================================================

    always @(*)
    begin
        case(state)

            S0  : balance = 0;
            S5  : balance = 5;
            S10 : balance = 10;
            S15 : balance = 15;
            S20 : balance = 20;
            S25 : balance = 25;

            default : balance = 0;

        endcase
    end

endmodule

vending_machine_tb.v
`timescale 1ns/1ps

module vending_machine_tb;

    reg clk;
    reg reset;

    reg coin5;
    reg coin10;

    reg selectA;
    reg selectB;

    wire dispenseA;
    wire dispenseB;

    wire [4:0] change;
    wire [5:0] balance;

    //=====================================================
    // DUT INSTANTIATION
    //=====================================================

    vending_machine uut(
        .clk(clk),
        .reset(reset),

        .coin5(coin5),
        .coin10(coin10),

        .selectA(selectA),
        .selectB(selectB),

        .dispenseA(dispenseA),
        .dispenseB(dispenseB),

        .change(change),
        .balance(balance)
    );

    //=====================================================
    // CLOCK GENERATION
    //=====================================================

    always #5 clk = ~clk;

    //=====================================================
    // TESTING
    //=====================================================

    initial
    begin

        $dumpfile("vending.vcd");
        $dumpvars(0, vending_machine_tb);

        clk = 0;
        reset = 1;

        coin5 = 0;
        coin10 = 0;

        selectA = 0;
        selectB = 0;

        #10;
        reset = 0;

        //=================================================
        // CASE 1
        // Buy Product A using 5 + 10
        //=================================================

        $display("CASE 1 : Product A Exact Payment");

        #10 coin5 = 1;
        #10 coin5 = 0;

        #10 coin10 = 1;
        #10 coin10 = 0;

        #10 selectA = 1;
        #10 selectA = 0;

        //=================================================
        // RESET
        //=================================================

        #20 reset = 1;
        #10 reset = 0;

        //=================================================
        // CASE 2
        // Buy Product B using 10 + 10
        //=================================================

        $display("CASE 2 : Product B Exact Payment");

        #10 coin10 = 1;
        #10 coin10 = 0;

        #10 coin10 = 1;
        #10 coin10 = 0;

        #10 selectB = 1;
        #10 selectB = 0;

        //=================================================
        // RESET
        //=================================================

        #20 reset = 1;
        #10 reset = 0;

        //=================================================
        // CASE 3
        // Product A with extra money
        // 10 + 10 = 20
        // Change = 5
        //=================================================

        $display("CASE 3 : Product A With Change");

        #10 coin10 = 1;
        #10 coin10 = 0;

        #10 coin10 = 1;
        #10 coin10 = 0;

        #10 selectA = 1;
        #10 selectA = 0;

        //=================================================
        // RESET
        //=================================================

        #20 reset = 1;
        #10 reset = 0;

        //=================================================
        // CASE 4
        // Product B with extra money
        // 10 + 10 + 5 = 25
        // Change = 5
        //=================================================

        $display("CASE 4 : Product B With Change");

        #10 coin10 = 1;
        #10 coin10 = 0;

        #10 coin10 = 1;
        #10 coin10 = 0;

        #10 coin5 = 1;
        #10 coin5 = 0;

        #10 selectB = 1;
        #10 selectB = 0;

        //=================================================
        // CASE 5
        // Insufficient balance
        //=================================================

        $display("CASE 5 : Insufficient Balance");

        #20 reset = 1;
        #10 reset = 0;

        #10 coin5 = 1;
        #10 coin5 = 0;

        #10 selectB = 1;
        #10 selectB = 0;

        //=================================================
        // END
        //=================================================

        #50;
        $finish;

    end

endmodule

vending.vcd
$date
	Tue May 12 14:33:33 2026
$end
$version
	Icarus Verilog
$end
$timescale
	1ps
$end
$scope module vending_machine_tb $end
$var wire 1 ! dispenseB $end
$var wire 1 " dispenseA $end
$var wire 5 # change [4:0] $end
$var wire 6 $ balance [5:0] $end
$var reg 1 % clk $end
$var reg 1 & coin10 $end
$var reg 1 ' coin5 $end
$var reg 1 ( reset $end
$var reg 1 ) selectA $end
$var reg 1 * selectB $end
$scope module uut $end
$var wire 1 % clk $end
$var wire 1 & coin10 $end
$var wire 1 ' coin5 $end
$var wire 1 ( reset $end
$var wire 1 ) selectA $end
$var wire 1 * selectB $end
$var parameter 32 + S0 $end
$var parameter 32 , S10 $end
$var parameter 32 - S15 $end
$var parameter 32 . S20 $end
$var parameter 32 / S25 $end
$var parameter 32 0 S5 $end
$var reg 6 1 balance [5:0] $end
$var reg 5 2 change [4:0] $end
$var reg 1 " dispenseA $end
$var reg 1 ! dispenseB $end
$var reg 3 3 next_state [2:0] $end
$var reg 3 4 state [2:0] $end
$upscope $end
$upscope $end
$enddefinitions $end
$comment Show the parameter values. $end
$dumpall
b1 0
b101 /
b100 .
b11 -
b10 ,
b0 +
$end
#0
$dumpvars
b0 4
b0 3
b0 2
b0 1
0*
0)
1(
0'
0&
0%
b0 $
b0 #
0"
0!
$end
#5000
1%
#10000
0%
0(
#15000
1%
#20000
b1 3
0%
1'
#25000
b101 $
b101 1
b10 3
b1 4
1%
#30000
b1 3
0%
0'
#35000
1%
#40000
b11 3
0%
1&
#45000
b1111 $
b1111 1
b101 3
b11 4
1%
#50000
b11 3
0%
0&
#55000
1%
#60000
1"
0%
1)
#65000
1%
#70000
0"
0%
0)
#75000
1%
#80000
0%
#85000
1%
#90000
b0 $
b0 1
b0 3
b0 4
0%
1(
#95000
1%
#100000
0%
0(
#105000
1%
#110000
b10 3
0%
1&
#115000
b1010 $
b1010 1
b100 3
b10 4
1%
#120000
b10 3
0%
0&
#125000
1%
#130000
b100 3
0%
1&
#135000
b10100 $
b10100 1
b100 4
1%
#140000
0%
0&
#145000
1%
#150000
1!
0%
1*
#155000
1%
#160000
0!
0%
0*
#165000
1%
#170000
0%
#175000
1%
#180000
b0 $
b0 1
b0 3
b0 4
0%
1(
#185000
1%
#190000
0%
0(
#195000
1%
#200000
b10 3
0%
1&
#205000
b1010 $
b1010 1
b100 3
b10 4
1%
#210000
b10 3
0%
0&
#215000
1%
#220000
b100 3
0%
1&
#225000
b10100 $
b10100 1
b100 4
1%
#230000
0%
0&
#235000
1%
#240000
b101 #
b101 2
1"
0%
1)
#245000
1%
#250000
b0 #
b0 2
0"
0%
0)
#255000
1%
#260000
0%
#265000
1%
#270000
b0 $
b0 1
b0 3
b0 4
0%
1(
#275000
1%
#280000
0%
0(
#285000
1%
#290000
b10 3
0%
1&
#295000
b1010 $
b1010 1
b100 3
b10 4
1%
#300000
b10 3
0%
0&
#305000
1%
#310000
b100 3
0%
1&
#315000
b10100 $
b10100 1
b100 4
1%
#320000
0%
0&
#325000
1%
#330000
b101 3
0%
1'
#335000
b11001 $
b11001 1
b101 4
1%
#340000
0%
0'
#345000
1%
#350000
b101 #
b101 2
1!
0%
1*
#355000
1%
#360000
b0 #
b0 2
0!
0%
0*
#365000
1%
#370000
0%
#375000
1%
#380000
b0 $
b0 1
b0 3
b0 4
0%
1(
#385000
1%
#390000
0%
0(
#395000
1%
#400000
b1 3
0%
1'
#405000
b101 $
b101 1
b10 3
b1 4
1%
#410000
b1 3
0%
0'
#415000
1%
#420000
0%
1*
#425000
1%
#430000
0%
0*
